{
  "proyectos": [
    {
      "id": "1",
      "nombre" : "proyecto terraza",
      "descripcion" : "construcci贸n de una terraza para un jardin",
      "disponibilidad" : "ocupado",
      "direccion" : "av siempre viva 1234",
      "ciudad" : "santiago"
    },
    {
      "id": "2",
      "nombre" : "proyecto cocina",
      "descripcion" : "reconstruccion de cocina en un departamento",
      "disponibilidad" : "disponible",
      "direccion" : "av siempre viva 1234",
      "ciudad" : "talca"
    },
    {
      "id": "3",
      "nombre" : "proyecto terraza",
      "descripcion" : "construcci贸n de una terraza para un jardin",
      "disponibilidad" : "ocupado",
      "direccion" : "av italia 1234",
      "ciudad" : "coquimbo"
    },
    {
      "id": "4",
      "nombre" : "proyecto dormitorio",
      "descripcion" : "construcci贸n de un dormitorio en un segundo piso",
      "disponibilidad" : "disponible",
      "direccion" : "av siempre viva 1234",
      "ciudad" : "coquimbo"
    },
    {
      "id": "5",
      "nombre" : "proyecto terraza",
      "descripcion" : "construcci贸n de una terraza para un jardin",
      "disponibilidad" : "disponible",
      "direccion" : "av siempre viva 1234",
      "ciudad" : "coquimbo"
    }
  ]
}